Metadata-Version: 2.1
Name: SWAG-DNN
Version: 0.1.31
Summary: Implimentation of this paper The SWAG Algorithm; a Mathematical Approach that Outperforms Traditional Deep Learning. Theory and Implementation https://arxiv.org/pdf/1811.11813.pdf
Home-page: https://github.com/pypa/sampleproject
Author: Saeid Safaei
Author-email: saeid.safaei79@gmail.com
License: UNKNOWN
Platform: UNKNOWN
Classifier: Programming Language :: Python :: 3
Classifier: License :: OSI Approved :: MIT License
Classifier: Operating System :: OS Independent
Requires-Python: >=3.7
License-File: LICENSE
